LICENSE
MANIFEST.in
README.md
setup.py
django_pgconninfo.egg-info/PKG-INFO
django_pgconninfo.egg-info/SOURCES.txt
django_pgconninfo.egg-info/dependency_links.txt
django_pgconninfo.egg-info/requires.txt
django_pgconninfo.egg-info/top_level.txt
django_pgconninfo.egg-info/zip-safe
pgconninfo/__init__.py