Metadata-Version: 1.1
Name: django-pgconninfo
Version: 0.9.2
Summary: PostgreSQL connection info from environment variables
Home-page: http://github.com/ihabhussein/django-pgconninfo
Author: Ihab Hussein
Author-email: ihab@ihabhussein.com
License: BSD
Keywords: PostgreSQL connection
Platform: UNKNOWN
Classifier: Development Status :: 4 - Beta
Classifier: License :: OSI Approved :: BSD License
Classifier: Programming Language :: Python :: 2
Classifier: Programming Language :: Python :: 2.7
Classifier: Programming Language :: Python :: 3
Classifier: Programming Language :: Python :: 3.4
Classifier: Programming Language :: Python :: 3.5
Classifier: Programming Language :: Python :: 3.6
Classifier: Topic :: Database
